Metadata-Version: 1.1
Name: queue-hlatype-status
Version: 0.13
Summary: write hlatyping db status
Home-page: https://github.com/jeremiahsavage/queue_hlatype_status
Author: Jeremiah H. Savage
Author-email: jeremiahsavage@gmail.com
License: Apache 2.0
Platform: UNKNOWN
Classifier: Development Status :: 3 - Alpha
Classifier: Intended Audience :: Developers
Classifier: License :: OSI Approved :: Apache Software License
Classifier: Programming Language :: Python
Classifier: Programming Language :: Python :: 3
